{
  "id": 2,
  "image": "/images/cars/L/Lotus/er9.webp",
  "class": "B",
  "brand": "Lotus",
  "model": "E-R9",
  "normalizedKey": "lotus_e_r9",
  "status": "in progress",
  "message": "Still adding data",
  "rarity": "Epic",
  "stars": 6,
  "keyCar": true,
  "country": "UK",
  "epics": 12,
  "obtainableVia": null,
  "added": "Supercharged Summer",
  "addedWith": "SE",
  "addedDate": "27/5/2024",
  "blueprints1Star": 0,
  "blueprints2Star": 26,
  "blueprints3Star": 34,
  "blueprints4Star": 46,
  "blueprints5Star": 61,
  "blueprints6Star": 73,
  "Tags": null
}