{
  "id": 2,
  "image": "/images/cars/L/Lamborghini/huracansupertrofeoevo.jpg",
  "class": "D",
  "brand": "Lamborghini",
  "model": "Huracán Super Trofeo Evo",
  "rarity": "Epic",
  "stars": 5,
  "keyCar": true,
  "country": "Italy",
  "epics": 8,
  "obtainableVia": null,
  "goldMaxRank": 3000,
  "goldTopSpeed": 303.7,
  "goldAcceleration": 82.59,
  "goldHandling": 63.48,
  "goldNitro": 54.41,
  "added": "Full Throttle",
  "addedWith": "GP",
  "addedDate": "10/12/2020",
  "blueprints1Star": 0,
  "blueprints2Star": 22,
  "blueprints3Star": 30,
  "blueprints4Star": 35,
  "blueprints5Star": 38,
  "blueprints6Star": null,
  "Total upgrade cost": null,
  "Total GL points": null,
  "Garage_Lvl": null,
  "Nitro_TS": null,
  "Perfect_Nitro_TS": null,
  "Tags": "Europe",
  "Unnamed: 16": "315,8",
  "Total_BPs": 125,
  "Unnamed: 32": 13000,
  "Cost epic": 0
}
