{
  "id": 1,
  "image": "/images/cars/S/SpaniaGTA/2015gtaspano.jpg",
  "class": "S",
  "brand": "Spania GTA",
  "model": "2015 GTA Spano",
  "normalizedKey": "spania_gta_2015_gta_spano",
  "status": "in progress",
  "message": "Still adding data",
  "sources": ["MEI"],
  "rarity": "Epic",
  "stars": 6,
  "country": "Spain",
  "epics": 16,
  "obtainableVia": [],
  "added": "City of Lights",
  "addedWith": "SE",
  "addedDate": "06/02/2023",
  "blueprints1Star": 85,
  "blueprints2Star": 25,
  "blueprints3Star": 29,
  "blueprints4Star": 38,
  "blueprints5Star": 54,
  "blueprints6Star": 69
}